LICENSE
README.md
pyproject.toml
setup.py
discord_limits/__init__.py
discord_limits/client.py
discord_limits/errors.py
discord_limits/helpers.py
discord_limits/rate_limits.py
discord_limits.egg-info/PKG-INFO
discord_limits.egg-info/SOURCES.txt
discord_limits.egg-info/dependency_links.txt
discord_limits.egg-info/requires.txt
discord_limits.egg-info/top_level.txt
discord_limits/paths/__init__.py
discord_limits/paths/applicationPaths.py
discord_limits/paths/auditPaths.py
discord_limits/paths/autoModerationPaths.py
discord_limits/paths/channelPaths.py
discord_limits/paths/emojiPaths.py
discord_limits/paths/guildPaths.py
discord_limits/paths/interationsPaths.py
discord_limits/paths/invitePaths.py
discord_limits/paths/paths.py
discord_limits/paths/stagePaths.py
discord_limits/paths/stickerPaths.py
discord_limits/paths/userPaths.py
discord_limits/paths/webhookPaths.py