Metadata-Version: 2.1
Name: discord_limits
Version: 2.0.3
Summary: Make Discord API calls without having to worry about ratelimits.
Home-page: https://github.com/ninjafella/discord-API-limits
Author: ninjafella
License: MIT
Requires-Python: >=3.10
License-File: LICENSE
Requires-Dist: aiolimiter==1.1.0
Requires-Dist: aiohttp==3.9.5
